libdoc2testbench/__init__.py
libdoc2testbench/__main__.py
libdoc2testbench/arg_parser.py
libdoc2testbench/argument_api.py
libdoc2testbench/datatype_creator.py
libdoc2testbench/datatype_storage.py
libdoc2testbench/interaction_creator.py
libdoc2testbench/libdoc_generation.py
libdoc2testbench/pk_generator.py
libdoc2testbench/project_dump_builder.py
libdoc2testbench/testbench_import_generator.py
libdoc2testbench/uid_generator.py
libdoc2testbench/utils.py
libdoc2testbench/project_dump_model/__init__.py
libdoc2testbench/project_dump_model/itb_project_export.py
libdoc2testbench/project_dump_model/model_api.py
robotframework_libdoc2testbench-1.2.1.dist-info/LICENSE
robotframework_libdoc2testbench-1.2.1.dist-info/METADATA
robotframework_libdoc2testbench-1.2.1.dist-info/WHEEL
robotframework_libdoc2testbench-1.2.1.dist-info/entry_points.txt
robotframework_libdoc2testbench-1.2.1.dist-info/top_level.txt
robotframework_libdoc2testbench-1.2.1.dist-info/RECORD
