Metadata-Version: 2.1
Name: robotframework-libdoc2testbench
Version: 1.2.1
Summary: Robot Framework Libdoc Extension that generates imbus TestBench Library import formats.
Home-page: https://github.com/imbus/robotframework-libdoc2testbench
Author: imbus AG
License: Apache 2.0 License
Platform: any
Classifier: Environment :: Console
Classifier: Programming Language :: Python :: 3
Classifier: Programming Language :: Python :: 3.8
Classifier: Operating System :: OS Independent
Classifier: License :: OSI Approved :: Apache Software License
Classifier: Topic :: Software Development :: Testing
Classifier: Topic :: Software Development :: Testing :: Acceptance
Classifier: Framework :: Robot Framework
Requires-Python: >=3.8
Requires-Dist: robotframework <8.0,>=5.0
Requires-Dist: xsdata
Provides-Extra: dev
Requires-Dist: xsdata[cli] ; extra == 'dev'
Requires-Dist: black ; extra == 'dev'
Requires-Dist: flake8 ; extra == 'dev'
Requires-Dist: pylint ; extra == 'dev'
Requires-Dist: mypy ; extra == 'dev'
Requires-Dist: pytest ; extra == 'dev'
Requires-Dist: pytest-cov ; extra == 'dev'
Requires-Dist: pytest-spec ; extra == 'dev'
Requires-Dist: check-manifest ; extra == 'dev'
Requires-Dist: twine ; extra == 'dev'
Requires-Dist: wheel ; extra == 'dev'
Requires-Dist: setuptools ; extra == 'dev'
Requires-Dist: ruff ; extra == 'dev'
Requires-Dist: pip-tools ; extra == 'dev'
